aioring/__init__.py
aioring/aio.cp313-win_amd64.pyd
aioring/aio.pyx
aioring/aos.cp313-win_amd64.pyd
aioring/aos.pyx
aioring/asyncio_plugin.cp313-win_amd64.pyd
aioring/asyncio_plugin.pxd
aioring/asyncio_plugin.pyx
aioring/ring.cp313-win_amd64.pyd
aioring/ring.pxd
aioring/ring.pyx
aioring/ring_threaded.cp313-win_amd64.pyd
aioring/__pycache__/__init__.cpython-313.pyc
aioring/_ring/__init__.py
aioring/_ring/liburing.pxd
aioring/_ring/linux.pxd
aioring/_ring/ring_linux.pyx
aioring/_ring/ring_threaded.pyx
aioring/_ring/__pycache__/__init__.cpython-313.pyc
aioring-0.1.3.dist-info/licenses/LICENSE
tests/__init__.py
tests/aio/__init__.py
tests/aio/base.py
tests/aio/test_aio.py
tests/aos/__init__.py
tests/aos/base.py
tests/aos/test_cancel.py
tests/aos/test_close.py
tests/aos/test_open.py
tests/aos/test_pread.py
tests/aos/test_pwrite.py
tests/aos/test_stat.py
tests/ring/__init__.py
tests/ring/base.py
tests/ring/test_ring.py
aioring-0.1.3.dist-info/METADATA
aioring-0.1.3.dist-info/WHEEL
aioring-0.1.3.dist-info/top_level.txt
aioring-0.1.3.dist-info/RECORD
