Metadata-Version: 2.4
Name: aioring
Version: 0.1.3
Summary: Asynchronous I/O ring
Author: Paul K.
License: MIT License
Project-URL: source, https://github.com/paul70131/aioring
License-File: LICENSE
Dynamic: author
Dynamic: license-file
